pycobaltstrike/__init__.py
pycobaltstrike-1.0.0.dist-info/LICENSE
pycobaltstrike-1.0.0.dist-info/WHEEL
pycobaltstrike-1.0.0.dist-info/METADATA
pycobaltstrike-1.0.0.dist-info/RECORD
