Metadata-Version: 2.1
Name: pycobaltstrike
Version: 1.0.0
Summary: pycobaltstrike is a module to interact with cobaltstrike's external c2 
Author-email: Leon Jacobs <leonja511@gmail.com>
Requires-Python: >=3.10
Classifier: License :: OSI Approved :: GNU General Public License v3 or later (GPLv3+)
Project-URL: Source, https://github.com/leonjza/pycobaltstrike
